main.py
lightsequ-98.7.dist-info/METADATA
lightsequ-98.7.dist-info/WHEEL
lightsequ-98.7.dist-info/top_level.txt
lightsequ-98.7.dist-info/RECORD
